octoprint_smart_pow/__init__.py
octoprint_smart_pow/lib/__init__.py
octoprint_smart_pow/lib/async_interval_scheduler.py
octoprint_smart_pow/lib/conftest.py
octoprint_smart_pow/lib/discoverer.py
octoprint_smart_pow/lib/event_manager_helpers.py
octoprint_smart_pow/lib/events.py
octoprint_smart_pow/lib/smart_plug_client.py
octoprint_smart_pow/lib/thread_utils.py
octoprint_smart_pow/lib/tplink_plug_client.py
octoprint_smart_pow/lib/wait_utils.py
octoprint_smart_pow/lib/data/__init__.py
octoprint_smart_pow/lib/data/automatic_power_off.py
octoprint_smart_pow/lib/data/events.py
octoprint_smart_pow/lib/data/power_state.py
octoprint_smart_pow/lib/features/__init__.py
octoprint_smart_pow/lib/features/automatic_power_off.py
octoprint_smart_pow/lib/features/power_state_publisher.py
octoprint_smart_pow/lib/features/power_state_writer.py
octoprint_smart_pow/lib/features/printer_shutdown_predicate.py
octoprint_smart_pow/lib/mappers/__init__.py
octoprint_smart_pow/lib/mappers/automatic_power_off.py
octoprint_smart_pow/lib/mappers/events.py
octoprint_smart_pow/lib/mappers/power_state.py
octoprint_smart_pow/lib/tests/__init__.py
octoprint_smart_pow/lib/tests/test_async_interval_scheduler.py
octoprint_smart_pow/lib/tests/test_tplink_plug_client.py
octoprint_smart_pow/lib/tests/test_wait_utils.py
octoprint_smart_pow/static/js/smart_pow.js
octoprint_smart_pow/templates/smart_pow_tab.jinja2
SmartPow-0.0.0rc2.dist-info/METADATA
SmartPow-0.0.0rc2.dist-info/WHEEL
SmartPow-0.0.0rc2.dist-info/entry_points.txt
SmartPow-0.0.0rc2.dist-info/top_level.txt
SmartPow-0.0.0rc2.dist-info/RECORD
